{
  "file": "/Users/shenyijie/Desktop/MLWP project/01_本地副本_实验/reports/xgboost/submission_candidates/submission_umanglodaya_seed2024_blend_multi13_w60_t050.csv",
  "source": "seed2024 public-feedback anchored probability blend",
  "anchor": "submission_umanglodaya_xgb_smote_seed2024.csv",
  "anchor_public_score": 0.81412,
  "other": "multi13",
  "other_public_score": 0.81295,
  "anchor_weight": 0.6,
  "threshold_name": "t050",
  "threshold": 0.5,
  "positive_rate": 0.5356558335281739,
  "changed_vs_seed2024": 12
}
